{
  "fields": [
    {
      "aggregatable": false,
      "custom": false,
      "defaultValue": null,
      "extraTypeInfo": null,
      "filterable": false,
      "groupable": false,
      "inlineHelpText": null,
      "label": "Change Event ID",
      "name": "Id",
      "nillable": true,
      "picklistValues": [],
      "referenceTo": [],
      "relationshipName": null,
      "sortable": false,
      "type": "id"
    },
    {
      "aggregatable": false,
      "custom": false,
      "defaultValue": null,
      "extraTypeInfo": null,
      "filterable": false,
      "groupable": false,
      "inlineHelpText": null,
      "label": "Replay ID",
      "name": "ReplayId",
      "nillable": true,
      "picklistValues": [],
      "referenceTo": [],
      "relationshipName": null,
      "sortable": false,
      "type": "string"
    },
    {
      "aggregatable": false,
      "custom": false,
      "defaultValue": null,
      "extraTypeInfo": null,
      "filterable": false,
      "groupable": false,
      "inlineHelpText": null,
      "label": "Change Event Header",
      "name": "ChangeEventHeader",
      "nillable": false,
      "picklistValues": [],
      "referenceTo": [],
      "relationshipName": null,
      "sortable": false,
      "type": "complexvalue"
    },
    {
      "aggregatable": false,
      "custom": false,
      "defaultValue": null,
      "extraTypeInfo": null,
      "filterable": false,
      "groupable": false,
      "inlineHelpText": null,
      "label": "Owner ID",
      "name": "OwnerId",
      "nillable": true,
      "picklistValues": [],
      "referenceTo": [
        "User"
      ],
      "relationshipName": null,
      "sortable": false,
      "type": "reference"
    },
    {
      "aggregatable": false,
      "custom": false,
      "defaultValue": null,
      "extraTypeInfo": null,
      "filterable": false,
      "groupable": false,
      "inlineHelpText": null,
      "label": "<Entity>",
      "name": "Name",
      "nillable": true,
      "picklistValues": [],
      "referenceTo": [],
      "relationshipName": null,
      "sortable": false,
      "type": "string"
    },
    {
      "aggregatable": false,
      "custom": false,
      "defaultValue": null,
      "extraTypeInfo": null,
      "filterable": false,
      "groupable": false,
      "inlineHelpText": null,
      "label": "Created Date",
      "name": "CreatedDate",
      "nillable": true,
      "picklistValues": [],
      "referenceTo": [],
      "relationshipName": null,
      "sortable": false,
      "type": "datetime"
    },
    {
      "aggregatable": false,
      "custom": false,
      "defaultValue": null,
      "extraTypeInfo": null,
      "filterable": false,
      "groupable": false,
      "inlineHelpText": null,
      "label": "Created By ID",
      "name": "CreatedById",
      "nillable": true,
      "picklistValues": [],
      "referenceTo": [
        "User"
      ],
      "relationshipName": null,
      "sortable": false,
      "type": "reference"
    },
    {
      "aggregatable": false,
      "custom": false,
      "defaultValue": null,
      "extraTypeInfo": null,
      "filterable": false,
      "groupable": false,
      "inlineHelpText": null,
      "label": "Last Modified Date",
      "name": "LastModifiedDate",
      "nillable": true,
      "picklistValues": [],
      "referenceTo": [],
      "relationshipName": null,
      "sortable": false,
      "type": "datetime"
    },
    {
      "aggregatable": false,
      "custom": false,
      "defaultValue": null,
      "extraTypeInfo": null,
      "filterable": false,
      "groupable": false,
      "inlineHelpText": null,
      "label": "Last Modified By ID",
      "name": "LastModifiedById",
      "nillable": true,
      "picklistValues": [],
      "referenceTo": [
        "User"
      ],
      "relationshipName": null,
      "sortable": false,
      "type": "reference"
    },
    {
      "aggregatable": false,
      "custom": true,
      "defaultValue": null,
      "extraTypeInfo": null,
      "filterable": false,
      "groupable": false,
      "inlineHelpText": null,
      "label": "Department Name",
      "name": "Department_Name__c",
      "nillable": true,
      "picklistValues": [],
      "referenceTo": [],
      "relationshipName": null,
      "sortable": false,
      "type": "string"
    },
    {
      "aggregatable": false,
      "custom": true,
      "defaultValue": null,
      "extraTypeInfo": null,
      "filterable": false,
      "groupable": false,
      "inlineHelpText": null,
      "label": "Department Manager",
      "name": "Department_Manager__c",
      "nillable": true,
      "picklistValues": [],
      "referenceTo": [],
      "relationshipName": null,
      "sortable": false,
      "type": "string"
    },
    {
      "aggregatable": false,
      "custom": true,
      "defaultValue": null,
      "extraTypeInfo": null,
      "filterable": false,
      "groupable": false,
      "inlineHelpText": null,
      "label": "Email",
      "name": "Email__c",
      "nillable": true,
      "picklistValues": [],
      "referenceTo": [],
      "relationshipName": null,
      "sortable": false,
      "type": "email"
    },
    {
      "aggregatable": false,
      "custom": true,
      "defaultValue": null,
      "extraTypeInfo": null,
      "filterable": false,
      "groupable": false,
      "inlineHelpText": null,
      "label": "Phone",
      "name": "Phone__c",
      "nillable": true,
      "picklistValues": [],
      "referenceTo": [],
      "relationshipName": null,
      "sortable": false,
      "type": "phone"
    },
    {
      "aggregatable": false,
      "custom": true,
      "defaultValue": null,
      "extraTypeInfo": null,
      "filterable": false,
      "groupable": false,
      "inlineHelpText": null,
      "label": "Budget",
      "name": "Budget__c",
      "nillable": true,
      "picklistValues": [],
      "referenceTo": [],
      "relationshipName": null,
      "sortable": false,
      "type": "currency"
    },
    {
      "aggregatable": false,
      "custom": true,
      "defaultValue": null,
      "extraTypeInfo": null,
      "filterable": false,
      "groupable": false,
      "inlineHelpText": null,
      "label": "Expenses",
      "name": "Expenses__c",
      "nillable": true,
      "picklistValues": [],
      "referenceTo": [],
      "relationshipName": null,
      "sortable": false,
      "type": "currency"
    },
    {
      "aggregatable": false,
      "custom": true,
      "defaultValue": "Building A",
      "extraTypeInfo": null,
      "filterable": false,
      "groupable": false,
      "inlineHelpText": null,
      "label": "Location",
      "name": "Location__c",
      "nillable": true,
      "picklistValues": [
        {
          "active": true,
          "defaultValue": true,
          "label": "Building A",
          "validFor": null,
          "value": "Building A"
        },
        {
          "active": true,
          "defaultValue": false,
          "label": "Building B",
          "validFor": null,
          "value": "Building B"
        },
        {
          "active": true,
          "defaultValue": false,
          "label": "Building C",
          "validFor": null,
          "value": "Building C"
        },
        {
          "active": true,
          "defaultValue": false,
          "label": "Building D",
          "validFor": null,
          "value": "Building D"
        }
      ],
      "referenceTo": [],
      "relationshipName": null,
      "sortable": false,
      "type": "picklist"
    },
    {
      "aggregatable": false,
      "custom": true,
      "defaultValue": true,
      "extraTypeInfo": null,
      "filterable": false,
      "groupable": false,
      "inlineHelpText": null,
      "label": "Access Key ?",
      "name": "Access_Key__c",
      "nillable": false,
      "picklistValues": [],
      "referenceTo": [],
      "relationshipName": null,
      "sortable": false,
      "type": "boolean"
    }
  ],
  "label": "Change Event: Department",
  "childRelationships": [],
  "custom": false,
  "name": "Department__ChangeEvent",
  "queryable": false
}